{
    "url": "http://10.192.133.33/smc/index.php?option=com_content&view=article&id=676:-huawei-ne8000&catid=43:2011-11-14-08-37-12&Itemid=81",
    "text": "Huawei NE8000 Command Manual",
    "source": "http://10.192.133.33/smc/index.php?option=com_content&view=article&id=676:-huawei-ne8000&catid=43:2011-11-14-08-37-12&Itemid=81",
    "links": [
        {
            "href": "http://10.192.133.33/smc/index.php?option=com_content&view=article&id=676:-huawei-ne8000&catid=43:2011-11-14-08-37-12&Itemid=81",
            "text": "Huawei NE8000 Command Manual"
        }
    ],
    "content": "Huawei NE8000 Command Manual\n\nBasic CLI Commands for Huawei NE8000 Series Routers.\n\n1. Display Device Information:\n<display device>\n\n2. Show Interface Status:\n<display interface brief>\n\n3. Show MAC Address Table:\n<display mac-address>\n\n4. Show IP Routing Table:\n<display ip routing-table>\n\n5. Save Configuration:\n<save>\n\n6. System Information:\n<display version>\n\nFor more advanced configurations, please refer to the official documentation or contact support."
}